[
    {
        "name": "fourhubtech - timesheet.fourhubtech.com",
        "host": "82.180.142.165",
        "protocol": "ftp",
        "port": 21,
        "username": "u349028357.fourhubtech.com",
        "remotePath": "/public_html/timesheet.fourhubtech.com",
        "context": "dist",
        "uploadOnSave": false,
        "useTempFile": false,
        "openSsh": false
    },
    {
        "name": "timekeepinghub - dev",
        "host": "82.180.142.165",
        "protocol": "ftp",
        "port": 21,
        "username": "u349028357.timekeepinghub.com",
        "remotePath": "/public_html/dev.timekeepinghub",
        "context": "dist",
        "uploadOnSave": false,
        "useTempFile": false,
        "openSsh": false
    },
    {
        "name": "timekeepinghub - qa",
        "host": "82.180.142.165",
        "protocol": "ftp",
        "port": 21,
        "username": "u349028357.timekeepinghub.com",
        "remotePath": "/public_html/qa.timekeepinghub.com",
        "context": "dist",
        "uploadOnSave": false,
        "useTempFile": false,
        "openSsh": false
    },
    {
        "name": "timekeepinghub - preview",
        "host": "82.180.142.165",
        "protocol": "ftp",
        "port": 21,
        "username": "u349028357.timekeepinghub.com",
        "remotePath": "/public_html/preview.timekeepinghub.com",
        "context": "dist",
        "uploadOnSave": false,
        "useTempFile": false,
        "openSsh": false
    },
    {
        "name": "timekeepinghub - production",
        "host": "82.180.142.165",
        "protocol": "ftp",
        "port": 21,
        "username": "u349028357.timekeepinghub.com",
        "remotePath": "/public_html/timekeepinghub.com",
        "context": "dist",
        "uploadOnSave": false,
        "useTempFile": false,
        "openSsh": false
    }
]
